qs/__init__.py
qs/__main__.py
qs/qs.py
queryswap-0.0.4.3.dist-info/LICENSE
queryswap-0.0.4.3.dist-info/METADATA
queryswap-0.0.4.3.dist-info/WHEEL
queryswap-0.0.4.3.dist-info/top_level.txt
queryswap-0.0.4.3.dist-info/RECORD
