Metadata-Version: 2.1
Name: queryswap
Version: 0.0.4.3
Summary: A url query string swapper
Home-page: https://github.com/mikedesu/qs
Author: darkmage
Author-email: darkmagex6+github@bugcrowdninja.com
Project-URL: Bug Tracker, https://github.com/mikedesu/qs/issues
Classifier: Programming Language :: Python :: 3
Classifier: License :: OSI Approved :: MIT License
Classifier: Operating System :: OS Independent
Requires-Python: >=3.6
License-File: LICENSE
